api_pipe/__init__.py
api_pipe/api.py
api_pipe/config.py
api_pipe/directory.py
api_pipe/error.py
api_pipe/logger.py
api_pipe/manual_test_run.py
api_pipe/params.py
api_pipe/params_schema.py
api_pipe/steps/__init__.py
api_pipe/steps/fetch.py
api_pipe/steps/fetch_async.py
api_pipe/steps/filter.py
api_pipe/steps/key.py
api_pipe/steps/map.py
api_pipe/steps/select.py
api_pipe/steps/to_json.py
api_pipe/steps/to_python.py
api_pipe/url.py
api_pipe-2.0.26.dist-info/METADATA
api_pipe-2.0.26.dist-info/WHEEL
api_pipe-2.0.26.dist-info/entry_points.txt
api_pipe-2.0.26.dist-info/RECORD
