Metadata-Version: 2.1
Name: api-pipe
Version: 2.0.26
Summary: API Pipe
License: LGPL-3.0-or-later
Author: RomanLabs
Author-email: rromanotero@romanlabs.com
Requires-Python: >=3.11,<4.0
Classifier: License :: OSI Approved :: GNU Lesser General Public License v3 or later (LGPLv3+)
Classifier: Programming Language :: Python :: 3
Classifier: Programming Language :: Python :: 3.11
Classifier: Programming Language :: Python :: 3.12
Requires-Dist: httpx (>=0.26.0,<1.0.0)
Requires-Dist: rich (>=13.7.0,<14.0.0)
